file_organizer/__init__.py
file_organizer/cli.py
file_organizer/core.py
py_file_organizer-0.1.2.dist-info/licenses/LICENSE
py_file_organizer-0.1.2.dist-info/METADATA
py_file_organizer-0.1.2.dist-info/WHEEL
py_file_organizer-0.1.2.dist-info/entry_points.txt
py_file_organizer-0.1.2.dist-info/top_level.txt
py_file_organizer-0.1.2.dist-info/RECORD
