Metadata-Version: 2.4
Name: py_file_organizer
Version: 0.1.2
Summary: A simple tool to organize files into folders by type. To use as a CLI tool, use the command 'file-organizer' 
Author: Oteri Eyenike
Requires-Python: >=3.6
License-File: LICENSE
Dynamic: author
Dynamic: license-file
Dynamic: requires-python
Dynamic: summary
